pybridge/__init__.py
pybridge/pybridge.py
pybridge_mrt-1.3.0.dist-info/METADATA
pybridge_mrt-1.3.0.dist-info/WHEEL
pybridge_mrt-1.3.0.dist-info/top_level.txt
pybridge_mrt-1.3.0.dist-info/RECORD
