Metadata-Version: 2.1
Name: pybridge-mrt
Version: 1.3.0
Summary: A library for sharing data between python scripts
Author: Mohammad Reaza Taghdiri
Author-email: m40465271@gmail.com
